markdown_table_fixer/__init__.py
markdown_table_fixer/_version.py
markdown_table_fixer/blocked_pr_scanner.py
markdown_table_fixer/cli.py
markdown_table_fixer/exceptions.py
markdown_table_fixer/git_config.py
markdown_table_fixer/github_client.py
markdown_table_fixer/graphql_queries.py
markdown_table_fixer/models.py
markdown_table_fixer/pr_fixer.py
markdown_table_fixer/pr_scanner.py
markdown_table_fixer/progress_tracker.py
markdown_table_fixer/py.typed
markdown_table_fixer/rule_disabler.py
markdown_table_fixer/table_fixer.py
markdown_table_fixer/table_parser.py
markdown_table_fixer/table_validator.py
markdown_table_fixer-0.1.4.dist-info/METADATA
markdown_table_fixer-0.1.4.dist-info/WHEEL
markdown_table_fixer-0.1.4.dist-info/entry_points.txt
markdown_table_fixer-0.1.4.dist-info/licenses/LICENSE
markdown_table_fixer-0.1.4.dist-info/RECORD
