Metadata-Version: 2.4
Name: markdown-table-fixer
Version: 0.1.4
Summary: Markdown table formatter and linter with GitHub integration
Project-URL: Homepage, https://github.com/lfit/markdown-table-fixer
Project-URL: Repository, https://github.com/lfit/markdown-table-fixer.git
Project-URL: Bug Tracker, https://github.com/lfit/markdown-table-fixer/issues
Author-email: The Linux Foundation <releng@linuxfoundation.org>
License: Apache-2.0
License-File: LICENSE
Keywords: formatter,github,linter,markdown,pre-commit,table
Classifier: Development Status :: 4 - Beta
Classifier: Environment :: Console
Classifier: Intended Audience :: Developers
Classifier: License :: OSI Approved :: Apache Software License
Classifier: Operating System :: OS Independent
Classifier: Programming Language :: Python :: 3
Classifier: Programming Language :: Python :: 3.10
Classifier: Programming Language :: Python :: 3.11
Classifier: Programming Language :: Python :: 3.12
Classifier: Programming Language :: Python :: 3.13
Classifier: Programming Language :: Python :: 3.14
Classifier: Topic :: Software Development :: Quality Assurance
Classifier: Topic :: Text Processing :: Markup :: Markdown
Requires-Python: >=3.10
Requires-Dist: aiolimiter>=1.2.1
Requires-Dist: dependamerge>=0.1.19
Requires-Dist: httpx[http2]>=0.28.1
Requires-Dist: pydantic>=2.12.5
Requires-Dist: pyyaml>=6.0.3
Requires-Dist: rich>=14.2.0
Requires-Dist: tenacity>=9.1.2
Requires-Dist: typer>=0.20.0
Requires-Dist: wcwidth>=0.2.14
Provides-Extra: dev
Requires-Dist: mypy>=1.17.1; extra == 'dev'
Requires-Dist: pre-commit>=4.5.0; extra == 'dev'
Requires-Dist: pytest-asyncio>=1.1.0; extra == 'dev'
Requires-Dist: pytest-cov>=7.0.0; extra == 'dev'
Requires-Dist: pytest-mock>=3.15.1; extra == 'dev'
Requires-Dist: pytest>=9.0.2; extra == 'dev'
Requires-Dist: ruff>=0.14.8; extra == 'dev'
Requires-Dist: types-pyyaml>=6.0.12.20250915; extra == 'dev'
